{
  "packages": [],
  "env": {
    "PLUGIN1_ENV2": "override"
  },
  "shell": {
    "init_hook": [
      "echo 'Welcome to devbox!' > /dev/null"
    ],
    "scripts": {
      "run_test": [
        // This tests init hook and env included from plugin1
        "test -n \"$PLUGIN1_INIT_HOOK\" || exit 1",
        "test -n \"$PLUGIN1_ENV\" || exit 1",
        // This tests init hook and env included from plugin1a (via plugin1, with relative path)
        "test -n \"$PLUGIN1A_INIT_HOOK\" || exit 1",
        "test -n \"$PLUGIN1A_ENV\" || exit 1",
        // Test env override
        "if [ \"$PLUGIN1_ENV2\" != \"override\" ]; then exit 1; fi;",
        // test included scripts
        "devbox run plugin_1_script",
        "devbox run plugin_1A_script",
        // Test packages included recursively
        "hello",
        "cowsay 'Hello, world!'"
      ]
    }
  },
  "include": [
    {
      "type": "path",
      "path": "./plugin1"
    },
    {
      "type": "path",
      "path": "plugin2"
    },
    {
      "type": "path",
      "path": "./plugin3/plugin.json"
    }
    //"./plugin1",
    //"path:plugin2",
    //"./plugin3/plugin.json",
  ]
}
